{".class":"MypyFile","_fullname":"vehicle.Cabin.Seat.Row1.Pos3.Switch.Backrest","future_import_flags":[],"is_partial_stub_package":false,"is_stub":false,"names":{".class":"SymbolTable","Backrest":{".class":"SymbolTableNode","kind":"Gdef","node":{".class":"TypeInfo","_promote":[],"abstract_attributes":[],"alt_promote":null,"bases":["velocitas_sdk.model.Model"],"dataclass_transform_spec":null,"declared_metaclass":null,"defn":{".class":"ClassDef","fullname":"vehicle.Cabin.Seat.Row1.Pos3.Switch.Backrest.Backrest","name":"Backrest","type_vars":[]},"deletable_attributes":[],"flags":[],"fullname":"vehicle.Cabin.Seat.Row1.Pos3.Switch.Backrest.Backrest","has_param_spec_type":false,"metaclass_type":null,"metadata":{},"module_name":"vehicle.Cabin.Seat.Row1.Pos3.Switch.Backrest","mro":["vehicle.Cabin.Seat.Row1.Pos3.Switch.Backrest.Backrest","velocitas_sdk.model.Model","velocitas_sdk.model.Node","builtins.object"],"names":{".class":"SymbolTable","IsReclineBackwardEngaged":{".class":"SymbolTableNode","implicit":true,"kind":"Mdef","node":{".class":"Var","flags":["is_inferred"],"fullname":"vehicle.Cabin.Seat.Row1.Pos3.Switch.Backrest.Backrest.IsReclineBackwardEngaged","name":"IsReclineBackwardEngaged","type":"velocitas_sdk.model.DataPointBoolean"}},"IsReclineForwardEngaged":{".class":"SymbolTableNode","implicit":true,"kind":"Mdef","node":{".class":"Var","flags":["is_inferred"],"fullname":"vehicle.Cabin.Seat.Row1.Pos3.Switch.Backrest.Backrest.IsReclineForwardEngaged","name":"IsReclineForwardEngaged","type":"velocitas_sdk.model.DataPointBoolean"}},"Lumbar":{".class":"SymbolTableNode","implicit":true,"kind":"Mdef","node":{".class":"Var","flags":["is_inferred"],"fullname":"vehicle.Cabin.Seat.Row1.Pos3.Switch.Backrest.Backrest.Lumbar","name":"Lumbar","type":"vehicle.Cabin.Seat.Row1.Pos3.Switch.Backrest.Lumbar.Lumbar"}},"SideBolster":{".class":"SymbolTableNode","implicit":true,"kind":"Mdef","node":{".class":"Var","flags":["is_inferred"],"fullname":"vehicle.Cabin.Seat.Row1.Pos3.Switch.Backrest.Backrest.SideBolster","name":"SideBolster","type":"vehicle.Cabin.Seat.Row1.Pos3.Switch.Backrest.SideBolster.SideBolster"}},"__init__":{".class":"SymbolTableNode","kind":"Mdef","node":{".class":"FuncDef","abstract_status":0,"arg_kinds":[0,0,0],"arg_names":["self","name","parent"],"dataclass_transform_spec":null,"flags":[],"fullname":"vehicle.Cabin.Seat.Row1.Pos3.Switch.Backrest.Backrest.__init__","name":"__init__","type":null}}},"self_type":{".class":"TypeVarType","default":{".class":"AnyType","missing_import_name":null,"source_any":null,"type_of_any":4},"fullname":"vehicle.Cabin.Seat.Row1.Pos3.Switch.Backrest.Backrest.Self","id":0,"name":"Self","namespace":"","upper_bound":"vehicle.Cabin.Seat.Row1.Pos3.Switch.Backrest.Backrest","values":[],"variance":0},"slots":null,"tuple_type":null,"type_vars":[],"typeddict_type":null}},"DataPointBoolean":{".class":"SymbolTableNode","cross_ref":"velocitas_sdk.model.DataPointBoolean","kind":"Gdef"},"Lumbar":{".class":"SymbolTableNode","cross_ref":"vehicle.Cabin.Seat.Row1.Pos3.Switch.Backrest.Lumbar.Lumbar","kind":"Gdef"},"Model":{".class":"SymbolTableNode","cross_ref":"velocitas_sdk.model.Model","kind":"Gdef"},"SideBolster":{".class":"SymbolTableNode","cross_ref":"vehicle.Cabin.Seat.Row1.Pos3.Switch.Backrest.SideBolster.SideBolster","kind":"Gdef"},"__annotations__":{".class":"SymbolTableNode","kind":"Gdef","node":{".class":"Var","flags":["is_ready"],"fullname":"vehicle.Cabin.Seat.Row1.Pos3.Switch.Backrest.__annotations__","name":"__annotations__","type":{".class":"Instance","args":["builtins.str",{".class":"AnyType","missing_import_name":null,"source_any":null,"type_of_any":6}],"type_ref":"builtins.dict"}}},"__doc__":{".class":"SymbolTableNode","kind":"Gdef","node":{".class":"Var","flags":["is_ready"],"fullname":"vehicle.Cabin.Seat.Row1.Pos3.Switch.Backrest.__doc__","name":"__doc__","type":"builtins.str"}},"__file__":{".class":"SymbolTableNode","kind":"Gdef","node":{".class":"Var","flags":["is_ready"],"fullname":"vehicle.Cabin.Seat.Row1.Pos3.Switch.Backrest.__file__","name":"__file__","type":"builtins.str"}},"__name__":{".class":"SymbolTableNode","kind":"Gdef","node":{".class":"Var","flags":["is_ready"],"fullname":"vehicle.Cabin.Seat.Row1.Pos3.Switch.Backrest.__name__","name":"__name__","type":"builtins.str"}},"__package__":{".class":"SymbolTableNode","kind":"Gdef","node":{".class":"Var","flags":["is_ready"],"fullname":"vehicle.Cabin.Seat.Row1.Pos3.Switch.Backrest.__package__","name":"__package__","type":"builtins.str"}},"__path__":{".class":"SymbolTableNode","kind":"Gdef","node":{".class":"Var","flags":["is_ready"],"fullname":"vehicle.Cabin.Seat.Row1.Pos3.Switch.Backrest.__path__","name":"__path__","type":{".class":"Instance","args":["builtins.str"],"type_ref":"builtins.list"}}}},"path":"/workspaces/velocitas_example/gen/vehicle_model/vehicle/Cabin/Seat/Row1/Pos3/Switch/Backrest/__init__.py"}