{"id":"fnmatch","path":"/home/vscode/.vscode-server/extensions/ms-python.mypy-type-checker-2023.6.0/bundled/libs/mypy/typeshed/stdlib/fnmatch.pyi","mtime":1699197088,"size":339,"hash":"05dc6b9252c7ced1c1ce0d8e6f6e90d1ac542e681df99f36c5136f63d861ff96","data_mtime":1699041322,"dependencies":["collections.abc","typing","builtins","abc"],"suppressed":[],"options":{"disallow_any_expr":false,"warn_return_any":false,"strict_equality":false,"always_false":[],"new_type_inference":false,"follow_imports":"normal","local_partial_types":false,"enabled_error_codes":[],"always_true":[],"disabled_error_codes":[],"plugins":[],"disallow_any_decorated":false,"disallow_subclassing_any":false,"disable_bytearray_promotion":false,"strict_concatenate":false,"disable_memoryview_promotion":false,"disable_error_code":[],"check_untyped_defs":true,"disallow_untyped_calls":false,"strict_optional":true,"ignore_errors":false,"extra_checks":false,"platform":"linux","disallow_untyped_decorators":false,"disallow_any_generics":false,"disallow_any_explicit":false,"ignore_missing_imports":false,"implicit_optional":false,"implicit_reexport":true,"mypyc":false,"disallow_untyped_defs":false,"warn_no_return":true,"disallow_any_unimported":false,"warn_unreachable":false,"enable_error_code":[],"allow_redefinition":false,"warn_unused_ignores":false,"allow_untyped_globals":false,"disallow_incomplete_defs":false,"follow_imports_for_stubs":false,"bazel":false},"dep_prios":[5,5,5,30],"dep_lines":[1,2,1,1],"interface_hash":"e87d50e4864abbd3df4c7627de567601fa9193528591a8681a9b3bc87caf28fb","version_id":"1.6.1","ignore_all":true,"plugin_data":null}