{"data_mtime":1699276451,"dep_lines":[15,8,1,1,1,1],"dep_prios":[5,5,5,30,30,30],"dependencies":["vehicle.Body.Windshield.Rear.Wiping.System","velocitas_sdk.model","builtins","abc","typing","velocitas_sdk"],"hash":"49ed4368cda4183dfc43b6938e1af1433463a579c4cec59e859852d366b799e5","id":"vehicle.Body.Windshield.Rear.Wiping","ignore_all":true,"interface_hash":"a157c3091b11e5982aa59d9ee6ab1996008048544ed0f1af15c77f5792b9a8ee","mtime":1699197120,"options":{"allow_redefinition":false,"allow_untyped_globals":false,"always_false":[],"always_true":[],"bazel":false,"check_untyped_defs":true,"disable_bytearray_promotion":false,"disable_error_code":[],"disable_memoryview_promotion":false,"disabled_error_codes":[],"disallow_any_decorated":false,"disallow_any_explicit":false,"disallow_any_expr":false,"disallow_any_generics":false,"disallow_any_unimported":false,"disallow_incomplete_defs":false,"disallow_subclassing_any":false,"disallow_untyped_calls":false,"disallow_untyped_decorators":false,"disallow_untyped_defs":false,"enable_error_code":[],"enabled_error_codes":[],"extra_checks":false,"follow_imports":"normal","follow_imports_for_stubs":false,"ignore_errors":false,"ignore_missing_imports":false,"implicit_optional":false,"implicit_reexport":true,"local_partial_types":false,"mypyc":false,"new_type_inference":false,"platform":"linux","plugins":[],"strict_concatenate":false,"strict_equality":false,"strict_optional":true,"warn_no_return":true,"warn_return_any":false,"warn_unreachable":false,"warn_unused_ignores":false},"path":"/workspaces/velocitas_example/gen/vehicle_model/vehicle/Body/Windshield/Rear/Wiping/__init__.py","plugin_data":null,"size":2250,"suppressed":[],"version_id":"1.6.1"}